runjenkins.py
runjenkins-2018.5.4.47356.dist-info/METADATA
runjenkins-2018.5.4.47356.dist-info/RECORD
runjenkins-2018.5.4.47356.dist-info/WHEEL
runjenkins-2018.5.4.47356.dist-info/entry_points.txt
runjenkins-2018.5.4.47356.dist-info/top_level.txt
