Metadata-Version: 2.1
Name: runjenkins
Version: 2018.5.4.47356
Summary: Run jenkins jobs from the cli using yaml configs
Home-page: https://github.com/hughsaunders/runjenkins
Author: Hugh Saunders
Author-email: hugh@wherenow.org
License: Apache
Platform: UNKNOWN
Requires-Python: >=3
Requires-Dist: click (==6.7)
Requires-Dist: python-jenkins (==0.4.15)
Requires-Dist: pyyaml (==3.12)
